ipnpy/__init__.py
ipnpy/contracts/__init__.py
ipnpy/contracts/eth/__init__.py
ipnpy/contracts/eth/abi.py
ipnpy/contracts/eth/token.py
ipnpy/contracts/tron/__init__.py
ipnpy/contracts/tron/abi.py
ipnpy/contracts/tron/token.py
ipnpy/exceptions/__init__.py
ipnpy/exceptions/exceptions.py
ipnpy/ipn/__init__.py
ipnpy/ipn/tools.py
ipnpy/rpc/__init__.py
ipnpy/rpc/enums.py
ipnpy/rpc/evm.py
ipnpy/rpc/tron.py
ipnpy/schemes/__init__.py
ipnpy/schemes/enums.py
ipnpy/schemes/ipn_api.py
ipnpy/schemes/webhook.py
ipnpy-0.0.1.dist-info/LICENSE
ipnpy-0.0.1.dist-info/METADATA
ipnpy-0.0.1.dist-info/WHEEL
ipnpy-0.0.1.dist-info/top_level.txt
ipnpy-0.0.1.dist-info/RECORD
