Metadata-Version: 2.1
Name: ipnpy
Version: 0.0.1
Summary: IPN Python 3.9+ Library
Home-page: https://github.com/IPNTools/ipn-py
Author: IPN Team
Author-email: ipncode@gmail.com
License: MIT
Platform: UNKNOWN
Classifier: Development Status :: 3 - Alpha
Classifier: Intended Audience :: Developers
Classifier: Intended Audience :: Customer Service
Classifier: License :: OSI Approved :: MIT License
Classifier: Operating System :: MacOS
Classifier: Operating System :: Microsoft :: Windows
Classifier: Operating System :: POSIX
Classifier: Natural Language :: English
Classifier: Programming Language :: Python :: 3.9
Classifier: Programming Language :: Python :: 3.10
Classifier: Programming Language :: Python :: 3.11
License-File: LICENSE
Requires-Dist: requests
Requires-Dist: pydantic
Requires-Dist: web3
Requires-Dist: base58
Requires-Dist: tronpy
